doc/create_conf_doc.py
doc/generate_variables_file.py
nabu/__init__.py
nabu/tests.py
nabu/testutils.py
nabu/utils.py
nabu/app/__init__.py
nabu/app/bootstrap.py
nabu/app/bootstrap_stitching.py
nabu/app/cast_volume.py
nabu/app/cli_configs.py
nabu/app/compare_volumes.py
nabu/app/composite_cor.py
nabu/app/create_distortion_map_from_poly.py
nabu/app/diag_to_pix.py
nabu/app/diag_to_rot.py
nabu/app/double_flatfield.py
nabu/app/estimate_motion.py
nabu/app/flip_volume_vertically.py
nabu/app/histogram.py
nabu/app/multicor.py
nabu/app/parse_reconstruction_log.py
nabu/app/pcaflats.py
nabu/app/prepare_weights_double.py
nabu/app/reconstruct.py
nabu/app/reconstruct_helical.py
nabu/app/reduce_dark_flat.py
nabu/app/rotate.py
nabu/app/shrink_dataset.py
nabu/app/stitching.py
nabu/app/utils.py
nabu/app/validator.py
nabu/app/tests/__init__.py
nabu/app/tests/test_reduce_dark_flat.py
nabu/cuda/__init__.py
nabu/cuda/kernel.py
nabu/cuda/processing.py
nabu/cuda/utils.py
nabu/cuda/src/ElementOp.cu
nabu/cuda/src/backproj.cu
nabu/cuda/src/backproj_polar.cu
nabu/cuda/src/boundary.h
nabu/cuda/src/clip_circle.cu
nabu/cuda/src/cone.cu
nabu/cuda/src/convolution.cu
nabu/cuda/src/dfi_fftshift.cu
nabu/cuda/src/flatfield.cu
nabu/cuda/src/fourier_wavelets.cu
nabu/cuda/src/halftomo.cu
nabu/cuda/src/helical_padding.cu
nabu/cuda/src/hierarchical_backproj.cu
nabu/cuda/src/histogram.cu
nabu/cuda/src/interpolation.cu
nabu/cuda/src/medfilt.cu
nabu/cuda/src/normalization.cu
nabu/cuda/src/padding.cu
nabu/cuda/src/proj.cu
nabu/cuda/src/rotation.cu
nabu/cuda/src/transpose.cu
nabu/cuda/tests/__init__.py
nabu/estimation/__init__.py
nabu/estimation/alignment.py
nabu/estimation/cor.py
nabu/estimation/cor_sino.py
nabu/estimation/distortion.py
nabu/estimation/focus.py
nabu/estimation/motion.py
nabu/estimation/tilt.py
nabu/estimation/translation.py
nabu/estimation/utils.py
nabu/estimation/tests/__init__.py
nabu/estimation/tests/test_alignment.py
nabu/estimation/tests/test_cor.py
nabu/estimation/tests/test_focus.py
nabu-2025.2.3.dist-info/licenses/LICENSE
nabu-2025.2.3.dist-info/METADATA
nabu-2025.2.3.dist-info/WHEEL
nabu-2025.2.3.dist-info/entry_points.txt
nabu-2025.2.3.dist-info/top_level.txt
nabu-2025.2.3.dist-info/RECORD
